my_project85/__init__.py
my_project85/config.py
my_project85/essential.py
my_project85/log_configs.py
my_project85/main.py
my_project85/scrapping.py
my_project85/utils.py
my_project85-0.1.1.dist-info/METADATA
my_project85-0.1.1.dist-info/WHEEL
my_project85-0.1.1.dist-info/RECORD
